{
  "copilot:translate-to-chinese": [
    {
      "modifiers": [
        "Ctrl",
        "Mod"
      ],
      "key": "T"
    },
    {
      "modifiers": [
        "Alt"
      ],
      "key": "T"
    }
  ],
  "editor:open-link-in-new-leaf": [],
  "obsidian-tasks-plugin:toggle-done": [
    {
      "modifiers": [
        "Mod"
      ],
      "key": "Enter"
    }
  ],
  "file-explorer:new-file": [],
  "workspace:new-tab": [],
  "obsidian-tasks-plugin:edit-task": [
    {
      "modifiers": [
        "Mod"
      ],
      "key": "T"
    }
  ],
  "quickadd:choice:5b567b91-e155-46d5-9c46-4bede568028a": [
    {
      "modifiers": [
        "Mod",
        "Shift"
      ],
      "key": "Enter"
    }
  ]
}